{
  "base_station_set": {
    "of:1000000000000013": {
      "name": "BS19",
      "mec_id": "eff4f6a1-8756-42d6-82fa-47eb7b661b9d",
      "links": {
        "of:1000000000000017": {
          "port": "9",
          "latency": 0.63
        },
        "of:100000000000000e": {
          "port": "5",
          "latency": 0.74
        },
        "of:100000000000000f": {
          "port": "8",
          "latency": 0.86
        },
        "of:100000000000001e": {
          "port": "7",
          "latency": 0.6
        },
        "of:100000000000001a": {
          "port": "3",
          "latency": 0.86
        },
        "of:1000000000000012": {
          "port": "5",
          "latency": 0.9
        },
        "of:1000000000000002": {
          "port": "5",
          "latency": 0.91
        }
      },
      "wireless_latency": 0.18
    },
    "of:1000000000000014": {
      "name": "BS20",
      "mec_id": "9f76d814-8a2d-4c59-ad48-9321e1930cab",
      "links": {
        "of:1000000000000007": {
          "port": "8",
          "latency": 0.57
        },
        "of:1000000000000018": {
          "port": "10",
          "latency": 0.68
        },
        "of:1000000000000009": {
          "port": "8",
          "latency": 0.71
        },
        "of:1000000000000006": {
          "port": "4",
          "latency": 0.7
        },
        "of:100000000000000c": {
          "port": "8",
          "latency": 0.89
        },
        "of:1000000000000005": {
          "port": "8",
          "latency": 0.53
        },
        "of:100000000000001f": {
          "port": "10",
          "latency": 0.76
        },
        "of:1000000000000011": {
          "port": "8",
          "latency": 0.98
        },
        "of:1000000000000001": {
          "port": "9",
          "latency": 0.62
        }
      },
      "wireless_latency": 0.23
    },
    "of:1000000000000015": {
      "name": "BS21",
      "mec_id": "d960d678-4337-4e0a-acda-1cada34a5caf",
      "links": {
        "of:1000000000000019": {
          "port": "4",
          "latency": 0.94
        },
        "of:100000000000000e": {
          "port": "6",
          "latency": 0.61
        },
        "of:100000000000001c": {
          "port": "4",
          "latency": 0.85
        },
        "of:100000000000001e": {
          "port": "8",
          "latency": 0.58
        },
        "of:100000000000000f": {
          "port": "5",
          "latency": 0.86
        },
        "of:100000000000000d": {
          "port": "5",
          "latency": 0.54
        },
        "of:1000000000000002": {
          "port": "6",
          "latency": 0.87
        }
      },
      "wireless_latency": 0.13
    },
    "of:1000000000000016": {
      "name": "BS22",
      "mec_id": "5d810ef6-d575-4a8b-8d03-fc98fffca96b",
      "links": {
        "of:1000000000000000": {
          "port": "4",
          "latency": 0.89
        },
        "of:1000000000000008": {
          "port": "5",
          "latency": 0.89
        },
        "of:1000000000000005": {
          "port": "9",
          "latency": 0.89
        },
        "of:100000000000001b": {
          "port": "7",
          "latency": 0.83
        },
        "of:1000000000000003": {
          "port": "2",
          "latency": 0.92
        }
      },
      "wireless_latency": 0.27
    },
    "of:1000000000000010": {
      "name": "BS16",
      "mec_id": "27692726-de6f-49d3-b98d-d0ba179a27ee",
      "links": {
        "of:1000000000000012": {
          "port": "4",
          "latency": 0.87
        },
        "of:1000000000000003": {
          "port": "6",
          "latency": 0.74
        },
        "of:100000000000000a": {
          "port": "5",
          "latency": 0.84
        },
        "of:1000000000000017": {
          "port": "7",
          "latency": 0.86
        },
        "of:1000000000000008": {
          "port": "8",
          "latency": 0.89
        }
      },
      "wireless_latency": 0.23
    },
    "of:1000000000000011": {
      "name": "BS17",
      "mec_id": "e891b6ed-79c9-4d81-8a7a-280112234174",
      "links": {
        "of:1000000000000006": {
          "port": "7",
          "latency": 0.61
        },
        "of:1000000000000014": {
          "port": "8",
          "latency": 0.98
        },
        "of:100000000000000c": {
          "port": "11",
          "latency": 0.81
        },
        "of:1000000000000005": {
          "port": "12",
          "latency": 0.72
        },
        "of:1000000000000001": {
          "port": "4",
          "latency": 0.85
        },
        "of:1000000000000018": {
          "port": "9",
          "latency": 0.88
        },
        "of:1000000000000009": {
          "port": "6",
          "latency": 0.57
        },
        "of:1000000000000007": {
          "port": "5",
          "latency": 0.7
        },
        "of:100000000000001f": {
          "port": "9",
          "latency": 0.51
        }
      },
      "wireless_latency": 0.13
    },
    "of:1000000000000012": {
      "name": "BS18",
      "mec_id": "1e496c0a-08e0-4467-805f-573446bd7bea",
      "links": {
        "of:1000000000000017": {
          "port": "8",
          "latency": 0.58
        },
        "of:1000000000000003": {
          "port": "7",
          "latency": 0.81
        },
        "of:1000000000000013": {
          "port": "5",
          "latency": 0.9
        },
        "of:100000000000000a": {
          "port": "6",
          "latency": 0.87
        },
        "of:1000000000000010": {
          "port": "6",
          "latency": 0.87
        }
      },
      "wireless_latency": 0.24
    },
    "of:1000000000000017": {
      "name": "BS23",
      "mec_id": "6c28f6f2-9248-46db-921b-440fb11d6b65",
      "links": {
        "of:100000000000000a": {
          "port": "4",
          "latency": 0.63
        },
        "of:1000000000000010": {
          "port": "5",
          "latency": 0.86
        },
        "of:1000000000000003": {
          "port": "5",
          "latency": 0.54
        },
        "of:1000000000000008": {
          "port": "7",
          "latency": 0.81
        },
        "of:100000000000000f": {
          "port": "7",
          "latency": 0.89
        },
        "of:1000000000000013": {
          "port": "8",
          "latency": 0.63
        },
        "of:100000000000001b": {
          "port": "8",
          "latency": 0.84
        },
        "of:100000000000000e": {
          "port": "8",
          "latency": 0.97
        },
        "of:1000000000000012": {
          "port": "6",
          "latency": 0.58
        }
      },
      "wireless_latency": 0.22
    },
    "of:1000000000000018": {
      "name": "BS24",
      "mec_id": "7e6b3dea-c0ba-42ad-af03-b8619494835f",
      "links": {
        "of:1000000000000001": {
          "port": "3",
          "latency": 0.69
        },
        "of:1000000000000009": {
          "port": "10",
          "latency": 0.53
        },
        "of:1000000000000000": {
          "port": "6",
          "latency": 0.54
        },
        "of:1000000000000007": {
          "port": "10",
          "latency": 0.56
        },
        "of:1000000000000014": {
          "port": "10",
          "latency": 0.68
        },
        "of:100000000000001f": {
          "port": "11",
          "latency": 0.74
        },
        "of:100000000000000c": {
          "port": "10",
          "latency": 0.93
        },
        "of:100000000000001b": {
          "port": "9",
          "latency": 0.52
        },
        "of:1000000000000005": {
          "port": "11",
          "latency": 0.63
        },
        "of:1000000000000011": {
          "port": "10",
          "latency": 0.88
        },
        "of:1000000000000006": {
          "port": "6",
          "latency": 0.71
        }
      },
      "wireless_latency": 0.17
    },
    "of:1000000000000019": {
      "name": "BS25",
      "mec_id": "9381b65b-dcaa-4e13-9870-69830baacc5d",
      "links": {
        "of:1000000000000015": {
          "port": "6",
          "latency": 0.94
        },
        "of:1000000000000004": {
          "port": "3",
          "latency": 0.61
        },
        "of:100000000000001d": {
          "port": "2",
          "latency": 0.85
        },
        "of:100000000000001c": {
          "port": "5",
          "latency": 0.76
        },
        "of:100000000000000c": {
          "port": "6",
          "latency": 0.89
        }
      },
      "wireless_latency": 0.27
    },
    "of:100000000000000b": {
      "name": "BS11",
      "mec_id": "17c55b21-cf62-4c27-9d75-79c57cfdb76f",
      "links": {
        "of:100000000000001e": {
          "port": "3",
          "latency": 0.62
        },
        "of:1000000000000002": {
          "port": "2",
          "latency": 0.52
        },
        "of:100000000000001a": {
          "port": "2",
          "latency": 0.72
        }
      },
      "wireless_latency": 0.17
    },
    "of:100000000000000c": {
      "name": "BS12",
      "mec_id": "dfb4067f-c610-461b-9c7a-66063ff3c259",
      "links": {
        "of:1000000000000019": {
          "port": "3",
          "latency": 0.89
        },
        "of:1000000000000009": {
          "port": "7",
          "latency": 0.55
        },
        "of:1000000000000005": {
          "port": "4",
          "latency": 0.82
        },
        "of:100000000000001f": {
          "port": "8",
          "latency": 0.56
        },
        "of:1000000000000007": {
          "port": "6",
          "latency": 0.63
        },
        "of:1000000000000011": {
          "port": "7",
          "latency": 0.81
        },
        "of:1000000000000014": {
          "port": "7",
          "latency": 0.89
        },
        "of:100000000000001b": {
          "port": "6",
          "latency": 0.87
        },
        "of:1000000000000018": {
          "port": "8",
          "latency": 0.93
        },
        "of:1000000000000001": {
          "port": "5",
          "latency": 0.53
        }
      },
      "wireless_latency": 0.27
    },
    "of:100000000000000d": {
      "name": "BS13",
      "mec_id": "c8666fde-a18e-4b73-9b13-56082e27635b",
      "links": {
        "of:100000000000000e": {
          "port": "3",
          "latency": 0.5
        },
        "of:100000000000000f": {
          "port": "3",
          "latency": 0.72
        },
        "of:100000000000001e": {
          "port": "4",
          "latency": 0.69
        },
        "of:1000000000000015": {
          "port": "3",
          "latency": 0.54
        },
        "of:1000000000000002": {
          "port": "3",
          "latency": 0.56
        },
        "of:100000000000001c": {
          "port": "2",
          "latency": 0.52
        }
      },
      "wireless_latency": 0.14
    },
    "of:100000000000000e": {
      "name": "BS14",
      "mec_id": "c1f605ec-abd0-4978-af41-40f3497fdc7c",
      "links": {
        "of:1000000000000017": {
          "port": "5",
          "latency": 0.97
        },
        "of:1000000000000015": {
          "port": "4",
          "latency": 0.61
        },
        "of:100000000000000f": {
          "port": "4",
          "latency": 0.87
        },
        "of:100000000000001e": {
          "port": "5",
          "latency": 0.54
        },
        "of:1000000000000002": {
          "port": "8",
          "latency": 0.76
        },
        "of:1000000000000013": {
          "port": "3",
          "latency": 0.74
        },
        "of:100000000000000d": {
          "port": "7",
          "latency": 0.5
        }
      },
      "wireless_latency": 0.14
    },
    "of:100000000000000a": {
      "name": "BS10",
      "mec_id": "1a98dda1-fa19-44a8-aa53-f161ce6615ee",
      "links": {
        "of:1000000000000017": {
          "port": "4",
          "latency": 0.63
        },
        "of:1000000000000008": {
          "port": "6",
          "latency": 0.68
        },
        "of:1000000000000003": {
          "port": "4",
          "latency": 0.79
        },
        "of:1000000000000012": {
          "port": "3",
          "latency": 0.87
        },
        "of:1000000000000010": {
          "port": "4",
          "latency": 0.84
        }
      },
      "wireless_latency": 0.26
    },
    "of:100000000000000f": {
      "name": "BS15",
      "mec_id": "8b72963a-f260-4204-b1a2-295cc38b4ae3",
      "links": {
        "of:1000000000000002": {
          "port": "4",
          "latency": 1.0
        },
        "of:1000000000000017": {
          "port": "6",
          "latency": 0.89
        },
        "of:100000000000000d": {
          "port": "3",
          "latency": 0.72
        },
        "of:1000000000000013": {
          "port": "4",
          "latency": 0.86
        },
        "of:100000000000001c": {
          "port": "3",
          "latency": 0.83
        },
        "of:1000000000000015": {
          "port": "5",
          "latency": 0.86
        },
        "of:100000000000001e": {
          "port": "6",
          "latency": 0.78
        },
        "of:100000000000000e": {
          "port": "4",
          "latency": 0.87
        }
      },
      "wireless_latency": 0.2
    },
    "of:1000000000000002": {
      "name": "BS2",
      "mec_id": "3a7366cf-ad9c-410b-83a5-e1d0b195bd95",
      "links": {
        "of:100000000000000e": {
          "port": "2",
          "latency": 0.76
        },
        "of:1000000000000015": {
          "port": "2",
          "latency": 0.87
        },
        "of:100000000000001e": {
          "port": "2",
          "latency": 0.95
        },
        "of:100000000000000f": {
          "port": "2",
          "latency": 1.0
        },
        "of:1000000000000013": {
          "port": "2",
          "latency": 0.91
        },
        "of:100000000000000d": {
          "port": "2",
          "latency": 0.56
        },
        "of:100000000000000b": {
          "port": "2",
          "latency": 0.52
        }
      },
      "wireless_latency": 0.28
    },
    "of:1000000000000003": {
      "name": "BS3",
      "mec_id": "50f2fa3f-010d-404a-a7fa-0797ffe48482",
      "links": {
        "of:1000000000000008": {
          "port": "3",
          "latency": 0.91
        },
        "of:1000000000000017": {
          "port": "2",
          "latency": 0.54
        },
        "of:1000000000000012": {
          "port": "2",
          "latency": 0.81
        },
        "of:100000000000001b": {
          "port": "3",
          "latency": 0.65
        },
        "of:1000000000000016": {
          "port": "3",
          "latency": 0.92
        },
        "of:1000000000000010": {
          "port": "2",
          "latency": 0.74
        },
        "of:100000000000000a": {
          "port": "2",
          "latency": 0.79
        }
      },
      "wireless_latency": 0.28
    },
    "of:1000000000000004": {
      "name": "BS4",
      "mec_id": "830e24a8-fb68-4b28-a47b-2e8840f04a15",
      "links": {
        "of:1000000000000007": {
          "port": "3",
          "latency": 0.76
        },
        "of:1000000000000019": {
          "port": "2",
          "latency": 0.61
        },
        "of:1000000000000001": {
          "port": "10",
          "latency": 1.0
        }
      },
      "wireless_latency": 0.15
    },
    "of:1000000000000005": {
      "name": "BS5",
      "mec_id": "e6839bac-6fb3-4e7f-b0b4-e384fcf2e9e0",
      "links": {
        "of:1000000000000000": {
          "port": "2",
          "latency": 0.72
        },
        "of:1000000000000001": {
          "port": "6",
          "latency": 0.86
        },
        "of:1000000000000009": {
          "port": "3",
          "latency": 0.7
        },
        "of:1000000000000018": {
          "port": "4",
          "latency": 0.63
        },
        "of:1000000000000011": {
          "port": "3",
          "latency": 0.72
        },
        "of:1000000000000014": {
          "port": "3",
          "latency": 0.53
        },
        "of:1000000000000016": {
          "port": "4",
          "latency": 0.89
        },
        "of:100000000000001f": {
          "port": "4",
          "latency": 0.91
        },
        "of:1000000000000006": {
          "port": "3",
          "latency": 0.93
        },
        "of:100000000000000c": {
          "port": "3",
          "latency": 0.82
        },
        "of:100000000000001b": {
          "port": "4",
          "latency": 0.71
        }
      },
      "wireless_latency": 0.16
    },
    "of:1000000000000000": {
      "name": "BS0",
      "mec_id": "df8296a9-63f3-4c62-bf95-3c18ae07e220",
      "links": {
        "of:1000000000000016": {
          "port": "2",
          "latency": 0.89
        },
        "of:100000000000001f": {
          "port": "2",
          "latency": 0.92
        },
        "of:1000000000000005": {
          "port": "2",
          "latency": 0.72
        },
        "of:100000000000001b": {
          "port": "2",
          "latency": 0.79
        },
        "of:1000000000000018": {
          "port": "2",
          "latency": 0.54
        },
        "of:1000000000000008": {
          "port": "2",
          "latency": 0.66
        }
      },
      "wireless_latency": 0.17
    },
    "of:1000000000000001": {
      "name": "BS1",
      "mec_id": "d0a39d07-02f2-4d21-93d7-747c0dbd8bf8",
      "links": {
        "of:1000000000000005": {
          "port": "3",
          "latency": 0.86
        },
        "of:1000000000000014": {
          "port": "2",
          "latency": 0.62
        },
        "of:100000000000000c": {
          "port": "2",
          "latency": 0.53
        },
        "of:1000000000000018": {
          "port": "3",
          "latency": 0.69
        },
        "of:100000000000001f": {
          "port": "3",
          "latency": 0.87
        },
        "of:1000000000000011": {
          "port": "2",
          "latency": 0.85
        },
        "of:1000000000000007": {
          "port": "2",
          "latency": 0.8
        },
        "of:1000000000000004": {
          "port": "2",
          "latency": 1.0
        },
        "of:1000000000000006": {
          "port": "2",
          "latency": 0.85
        },
        "of:1000000000000009": {
          "port": "2",
          "latency": 0.9
        }
      },
      "wireless_latency": 0.2
    },
    "of:1000000000000006": {
      "name": "BS6",
      "mec_id": "e6e83424-209a-4ff5-8d68-418143ca81d1",
      "links": {
        "of:1000000000000001": {
          "port": "11",
          "latency": 0.85
        },
        "of:1000000000000011": {
          "port": "4",
          "latency": 0.61
        },
        "of:1000000000000014": {
          "port": "4",
          "latency": 0.7
        },
        "of:1000000000000009": {
          "port": "4",
          "latency": 0.99
        },
        "of:1000000000000018": {
          "port": "5",
          "latency": 0.71
        },
        "of:1000000000000007": {
          "port": "4",
          "latency": 0.65
        },
        "of:1000000000000005": {
          "port": "6",
          "latency": 0.93
        },
        "of:100000000000001f": {
          "port": "5",
          "latency": 0.81
        }
      },
      "wireless_latency": 0.3
    },
    "of:1000000000000007": {
      "name": "BS7",
      "mec_id": "c0d2a253-a19b-46ed-b072-7cefb3c4650f",
      "links": {
        "of:100000000000000c": {
          "port": "4",
          "latency": 0.63
        },
        "of:1000000000000004": {
          "port": "4",
          "latency": 0.76
        },
        "of:1000000000000011": {
          "port": "5",
          "latency": 0.7
        },
        "of:1000000000000001": {
          "port": "7",
          "latency": 0.8
        },
        "of:1000000000000009": {
          "port": "5",
          "latency": 0.96
        },
        "of:1000000000000018": {
          "port": "6",
          "latency": 0.56
        },
        "of:1000000000000014": {
          "port": "5",
          "latency": 0.57
        },
        "of:1000000000000006": {
          "port": "8",
          "latency": 0.65
        },
        "of:100000000000001f": {
          "port": "6",
          "latency": 0.89
        }
      },
      "wireless_latency": 0.23
    },
    "of:1000000000000008": {
      "name": "BS8",
      "mec_id": "94783b7d-77a4-4359-8485-83e7c2251723",
      "links": {
        "of:1000000000000016": {
          "port": "5",
          "latency": 0.89
        },
        "of:1000000000000003": {
          "port": "3",
          "latency": 0.91
        },
        "of:1000000000000010": {
          "port": "3",
          "latency": 0.89
        },
        "of:100000000000000a": {
          "port": "3",
          "latency": 0.68
        },
        "of:100000000000001b": {
          "port": "5",
          "latency": 0.6
        },
        "of:1000000000000000": {
          "port": "7",
          "latency": 0.66
        },
        "of:1000000000000017": {
          "port": "3",
          "latency": 0.81
        }
      },
      "wireless_latency": 0.13
    },
    "of:1000000000000009": {
      "name": "BS9",
      "mec_id": "4ae01a92-7f0d-4f6a-b7da-a40888671e31",
      "links": {
        "of:1000000000000006": {
          "port": "9",
          "latency": 0.99
        },
        "of:1000000000000014": {
          "port": "6",
          "latency": 0.71
        },
        "of:1000000000000007": {
          "port": "7",
          "latency": 0.96
        },
        "of:100000000000001f": {
          "port": "7",
          "latency": 0.94
        },
        "of:1000000000000011": {
          "port": "6",
          "latency": 0.57
        },
        "of:100000000000000c": {
          "port": "5",
          "latency": 0.55
        },
        "of:1000000000000005": {
          "port": "5",
          "latency": 0.7
        },
        "of:1000000000000001": {
          "port": "8",
          "latency": 0.9
        },
        "of:1000000000000018": {
          "port": "7",
          "latency": 0.53
        }
      },
      "wireless_latency": 0.16
    },
    "of:100000000000001c": {
      "name": "BS28",
      "mec_id": "89698cc1-6041-4754-9c43-267707efa286",
      "links": {
        "of:1000000000000019": {
          "port": "6",
          "latency": 0.76
        },
        "of:100000000000001d": {
          "port": "3",
          "latency": 0.73
        },
        "of:100000000000000d": {
          "port": "4",
          "latency": 0.52
        },
        "of:100000000000000f": {
          "port": "9",
          "latency": 0.83
        },
        "of:1000000000000015": {
          "port": "7",
          "latency": 0.85
        }
      },
      "wireless_latency": 0.11
    },
    "of:100000000000001d": {
      "name": "BS29",
      "mec_id": "421ecf62-3f17-46fc-8406-0f0b61ee6927",
      "links": {
        "of:1000000000000019": {
          "port": "5",
          "latency": 0.85
        },
        "of:100000000000001c": {
          "port": "6",
          "latency": 0.73
        }
      },
      "wireless_latency": 0.21
    },
    "of:100000000000001e": {
      "name": "BS30",
      "mec_id": "d9810b6a-7489-4240-9d14-1fce23aa74cf",
      "links": {
        "of:100000000000000f": {
          "port": "6",
          "latency": 0.78
        },
        "of:100000000000000e": {
          "port": "7",
          "latency": 0.54
        },
        "of:1000000000000015": {
          "port": "8",
          "latency": 0.58
        },
        "of:1000000000000013": {
          "port": "7",
          "latency": 0.6
        },
        "of:100000000000000d": {
          "port": "6",
          "latency": 0.69
        },
        "of:1000000000000002": {
          "port": "7",
          "latency": 0.95
        },
        "of:100000000000000b": {
          "port": "4",
          "latency": 0.62
        }
      },
      "wireless_latency": 0.13
    },
    "of:100000000000001f": {
      "name": "BS31",
      "mec_id": "ff8e148d-2da6-4e81-baef-3c73ad61e898",
      "links": {
        "of:1000000000000009": {
          "port": "9",
          "latency": 0.94
        },
        "of:1000000000000000": {
          "port": "5",
          "latency": 0.92
        },
        "of:1000000000000018": {
          "port": "12",
          "latency": 0.74
        },
        "of:1000000000000014": {
          "port": "9",
          "latency": 0.76
        },
        "of:1000000000000006": {
          "port": "5",
          "latency": 0.81
        },
        "of:1000000000000007": {
          "port": "9",
          "latency": 0.89
        },
        "of:1000000000000011": {
          "port": "9",
          "latency": 0.51
        },
        "of:100000000000000c": {
          "port": "9",
          "latency": 0.56
        },
        "of:1000000000000005": {
          "port": "10",
          "latency": 0.91
        },
        "of:1000000000000001": {
          "port": "2",
          "latency": 0.87
        }
      },
      "wireless_latency": 0.22
    },
    "of:100000000000001a": {
      "name": "BS26",
      "mec_id": "6b38ca5a-d731-481f-be34-2e40874486cc",
      "links": {
        "of:1000000000000013": {
          "port": "6",
          "latency": 0.86
        },
        "of:100000000000000b": {
          "port": "3",
          "latency": 0.72
        }
      },
      "wireless_latency": 0.29
    },
    "of:100000000000001b": {
      "name": "BS27",
      "mec_id": "1e6cf0c6-c0c1-45b3-9784-5577a7934c0b",
      "links": {
        "of:100000000000000c": {
          "port": "7",
          "latency": 0.87
        },
        "of:1000000000000005": {
          "port": "7",
          "latency": 0.71
        },
        "of:1000000000000003": {
          "port": "8",
          "latency": 0.65
        },
        "of:1000000000000018": {
          "port": "11",
          "latency": 0.52
        },
        "of:1000000000000000": {
          "port": "3",
          "latency": 0.79
        },
        "of:1000000000000016": {
          "port": "6",
          "latency": 0.83
        },
        "of:1000000000000008": {
          "port": "4",
          "latency": 0.6
        },
        "of:1000000000000017": {
          "port": "10",
          "latency": 0.84
        }
      },
      "wireless_latency": 0.15
    }
  }
}